byebyepii/__init__.py
byebyepii/byebyepii.py
ByeByePii-1.0.1.dist-info/METADATA
ByeByePii-1.0.1.dist-info/WHEEL
ByeByePii-1.0.1.dist-info/top_level.txt
ByeByePii-1.0.1.dist-info/RECORD
