Metadata-Version: 2.1
Name: ByeByePii
Version: 1.0.1
Summary: A package for hashing personal identifiable information (PII).
Author: Falk
